longitudinal_tomography/__init__.py
longitudinal_tomography/__main__.py
longitudinal_tomography/_version.py
longitudinal_tomography/assertions.py
longitudinal_tomography/exceptions.py
longitudinal_tomography/shortcuts.py
longitudinal_tomography/compat/__init__.py
longitudinal_tomography/compat/fortran.py
longitudinal_tomography/compat/tomoscope.py
longitudinal_tomography/cpp_routines/__init__.py
longitudinal_tomography/cpp_routines/data_treatment.cpp
longitudinal_tomography/cpp_routines/data_treatment.h
longitudinal_tomography/cpp_routines/docs.h
longitudinal_tomography/cpp_routines/kick_and_drift.cpp
longitudinal_tomography/cpp_routines/kick_and_drift.h
longitudinal_tomography/cpp_routines/libtomo.cpp
longitudinal_tomography/cpp_routines/libtomo.cpython-311-x86_64-linux-gnu.so
longitudinal_tomography/cpp_routines/libtomo.h
longitudinal_tomography/cpp_routines/libtomo.pyi
longitudinal_tomography/cpp_routines/reconstruct.cpp
longitudinal_tomography/cpp_routines/reconstruct.h
longitudinal_tomography/cpp_routines/sin.h
longitudinal_tomography/cpp_routines/sincos.h
longitudinal_tomography/cpp_routines/tomolib_wrappers.py
longitudinal_tomography/cpp_routines/vdtcore_common.h
longitudinal_tomography/cuda_kernels/__init__.py
longitudinal_tomography/cuda_kernels/kick_and_drift.cu
longitudinal_tomography/cuda_kernels/reconstruct.cu
longitudinal_tomography/data/__init__.py
longitudinal_tomography/data/data_treatment.py
longitudinal_tomography/data/post_process.py
longitudinal_tomography/data/pre_process.py
longitudinal_tomography/data/profiles.py
longitudinal_tomography/python_routines/__init__.py
longitudinal_tomography/python_routines/data_treatment.py
longitudinal_tomography/python_routines/kick_and_drift_cuda.py
longitudinal_tomography/python_routines/kick_and_drift_cupy.py
longitudinal_tomography/python_routines/reconstruct_cuda.py
longitudinal_tomography/python_routines/reconstruct_cupy.py
longitudinal_tomography-3.5.2.dist-info/METADATA
longitudinal_tomography-3.5.2.dist-info/WHEEL
longitudinal_tomography-3.5.2.dist-info/top_level.txt
longitudinal_tomography-3.5.2.dist-info/RECORD
longitudinal_tomography-3.5.2.dist-info/licenses/LICENSE.txt
