Metadata-Version: 2.4
Name: longitudinal_tomography
Version: 3.5.2
Summary: A python library for longitudinal particle beam tomography
Author: Christoffer Hjertø Grindheim
Author-email: Simon Albright <simon.albright@cern.ch>, Bernardo Abreu Figueiredo <bernardo.abreu.figueiredo@cern.ch>, Anton Lu <anton.lu@cern.ch>
License: GNU General Public License version 3
Project-URL: homepage, https://gitlab.cern.ch/longitudinaltomography/tomographyv3
Project-URL: documentation, https://acc-py.web.cern.ch/gitlab/longitudinaltomography/tomographyv3/docs/stable/
Project-URL: repository, https://gitlab.cern.ch/longitudinaltomography/tomographyv3
Project-URL: changelog, https://gitlab.cern.ch/longitudinaltomography/tomographyv3/-/releases
Platform: Windows
Platform: Linux
Classifier: Programming Language :: Python :: 3 :: Only
Classifier: Programming Language :: Python :: 3.11
Classifier: License :: OSI Approved :: GNU General Public License v3 (GPLv3)
Classifier: Operating System :: OS Independent
Requires-Python: >=3.11
License-File: LICENSE.txt
Requires-Dist: matplotlib~=3.8
Requires-Dist: multipledispatch~=1.0
Requires-Dist: numpy~=1.25
Requires-Dist: scipy~=1.11
Provides-Extra: test
Requires-Dist: coverage; extra == "test"
Requires-Dist: coverage-badge; extra == "test"
Requires-Dist: flake8; extra == "test"
Requires-Dist: pylint; extra == "test"
Requires-Dist: pytest-cov; extra == "test"
Requires-Dist: pyyaml; extra == "test"
Provides-Extra: gpu
Requires-Dist: cupy; extra == "gpu"
Provides-Extra: doc
Requires-Dist: acc-py-sphinx; extra == "doc"
Requires-Dist: myst-parser; extra == "doc"
Requires-Dist: sphinx-copybutton; extra == "doc"
Dynamic: license-file
